[{"id":"user-image-profileicon.png","fileName":"profileicon.png","name":"profileicon","publicUrl":"https://assets.nicepagecdn.com/82713b8f/6261320/images/profileicon.png","size":19194,"hash":"B1K3ziNuASRuKcoJEZRaJVHW6O4=","width":1080,"height":1080,"folderId":null,"thumbnail":{"url":"https://assets.nicepagecdn.com/82713b8f/6261320/images/thumbnails/profileicon.png","width":150,"height":150},"usages":["91018987"]},{"id":"user-image-washingmachine.png","fileName":"washingmachine.png","name":"washingmachine","publicUrl":"https://assets.nicepagecdn.com/82713b8f/6261320/images/washingmachine.png","size":26260,"hash":"ubBilGOLukaeCBCKuiHZ1GygZz8=","width":512,"height":512,"folderId":null,"thumbnail":{"url":"https://assets.nicepagecdn.com/82713b8f/6261320/images/thumbnails/washingmachine.png","width":150,"height":150},"usages":["2656029026"]},{"id":"user-image-Service.png","fileName":"Service.png","name":"Service","publicUrl":"https://assets.nicepagecdn.com/82713b8f/6261320/images/Service.png","size":34667,"hash":"L2NZgZLz3SVvsJr3ui2kOofA7bU=","width":512,"height":512,"folderId":null,"thumbnail":{"url":"https://assets.nicepagecdn.com/82713b8f/6261320/images/thumbnails/Service.png","width":150,"height":150},"usages":["2656029026"]},{"id":"user-image-FL.png","fileName":"FL.png","name":"FL","publicUrl":"https://assets.nicepagecdn.com/82713b8f/6261320/images/FL.png","size":449614,"hash":"mzoTwIUVU/gh/QsU3gCN/+0Gb88=","width":960,"height":640,"folderId":null,"thumbnail":{"url":"https://assets.nicepagecdn.com/82713b8f/6261320/images/thumbnails/FL.png","width":150,"height":100},"usages":["2190724509","1278504881"]},{"id":"user-image-5.png","fileName":"5.png","name":"5","publicUrl":"https://assets.nicepagecdn.com/82713b8f/6261320/images/5.png","size":281496,"hash":"Ut/cBeKzdiKb8/UDvf2qjjm78UI=","width":1080,"height":1080,"folderId":null,"thumbnail":{"url":"https://assets.nicepagecdn.com/82713b8f/6261320/images/thumbnails/5.png","width":150,"height":150},"usages":["943624493"]},{"id":"user-image-3.png","fileName":"3.png","name":"3","publicUrl":"https://assets.nicepagecdn.com/82713b8f/6261320/images/3.png","size":136642,"hash":"3HisqB/MtlluM4qSyo1vltLMT3I=","width":1080,"height":1080,"folderId":null,"thumbnail":{"url":"https://assets.nicepagecdn.com/82713b8f/6261320/images/thumbnails/3.png","width":150,"height":150},"usages":["943624493"]},{"id":"user-image-4.png","fileName":"4.png","name":"4","publicUrl":"https://assets.nicepagecdn.com/82713b8f/6261320/images/4.png","size":70591,"hash":"b7pOimKGdlSRF4zQvMR88zM9qEQ=","width":1080,"height":1080,"folderId":null,"thumbnail":{"url":"https://assets.nicepagecdn.com/82713b8f/6261320/images/thumbnails/4.png","width":150,"height":150},"usages":["943624493"]}]